{
  "type": "Compass Connections",
  "version": {
    "$numberInt": "1"
  },
  "connections": [
    {
      "id": "5207fd74-e9f9-4a9e-b9d0-3af9ffa1c5e4",
      "lastUsed": {
        "$date": {
          "$numberLong": "1735378795402"
        }
      },
      "favorite": {
        "name": "Talha"
      },
      "savedConnectionType": "recent",
      "connectionOptions": {
        "connectionString": "mongodb://localhost:27017/",
        "oidc": {
          "serializedState": "eyJvaWRjUGx1Z2luU3RhdGVWZXJzaW9uIjowLCJzdGF0ZSI6W119"
        }
      }
    }
  ]
}